{"cameraMode":{"drawMode":0,"name":"Shaded","section":"Shading Mode"},"sceneLighting":true,"audioPlay":false,"sceneViewState":{"showFog":true,"showMaterialUpdate":false,"showSkybox":true,"showFlares":true,"showImageEffects":true,"showParticleSystems":true},"in2DMode":false,"pivot":{"x":-0.3157191574573517,"y":-1.0178580284118653,"z":-0.9512218236923218},"rotation":{"x":-0.3565630316734314,"y":0.12059532850980759,"z":-0.046467993408441547,"w":-0.9253085851669312},"size":10.0,"orthographic":false}